{
  "creator": "Yosys 0.60 (git sha1 5bafeb77dc71e054fa331ab9efa613e6fb0a1c49, clang++ 21.1.2 -fPIC -O3)",
  "modules": {
    "heichips25_ethernet": {
      "attributes": {
        "hdlname": "heichips25_ethernet",
        "top": "00000000000000000000000000000001",
        "src": "/home/ubudev/submit/heichips25-ethernet/src/heichips25_ethernet.sv:9.1-42.10"
      },
      "ports": {
        "ui_in": {
          "direction": "input",
          "bits": [ 2, 3, 4, 5, 6, 7, 8, 9 ]
        },
        "uo_out": {
          "direction": "output",
          "bits": [ "0", "0", "0", "0", "0", "0", "0", "0" ]
        },
        "uio_in": {
          "direction": "input",
          "bits": [ 10, 11, 12, 13, 14, 15, 16, 17 ]
        },
        "uio_out": {
          "direction": "output",
          "bits": [ "0", "0", "0", "0", "0", "0", "0", "0" ]
        },
        "uio_oe": {
          "direction": "output",
          "bits": [ "0", "0", "0", "0", "0", "0", "0", "0" ]
        },
        "ena": {
          "direction": "input",
          "bits": [ 18 ]
        },
        "clk": {
          "direction": "input",
          "bits": [ 19 ]
        },
        "rst_n": {
          "direction": "input",
          "bits": [ 20 ]
        },
        "ethernet_dp": {
          "direction": "output",
          "bits": [ 21 ]
        },
        "ethernet_dn": {
          "direction": "output",
          "bits": [ 22 ]
        }
      },
      "cells": {
        "$not$/home/ubudev/submit/heichips25-ethernet/src/heichips25_ethernet.sv:32$2": {
          "hide_name": 1,
          "type": "$not",
          "parameters": {
            "A_SIGNED": "00000000000000000000000000000000",
            "A_WIDTH": "00000000000000000000000000000001",
            "Y_WIDTH": "00000000000000000000000000000001"
          },
          "attributes": {
            "src": "/home/ubudev/submit/heichips25-ethernet/src/heichips25_ethernet.sv:32.17-32.26"
          },
          "port_directions": {
            "A": "input",
            "Y": "output"
          },
          "connections": {
            "A": [ 2 ],
            "Y": [ 23 ]
          }
        },
        "line_driver_0": {
          "hide_name": 0,
          "type": "line_driver",
          "parameters": {
          },
          "attributes": {
            "module_not_derived": "00000000000000000000000000000001",
            "src": "/home/ubudev/submit/heichips25-ethernet/src/heichips25_ethernet.sv:35.17-40.6"
          },
          "port_directions": {
            "ethernet_dn": "output",
            "ethernet_dp": "output",
            "in_n": "input",
            "in_p": "input"
          },
          "connections": {
            "ethernet_dn": [ 22 ],
            "ethernet_dp": [ 21 ],
            "in_n": [ 23 ],
            "in_p": [ 2 ]
          }
        }
      },
      "netnames": {
        "clk": {
          "hide_name": 0,
          "bits": [ 19 ],
          "attributes": {
            "src": "/home/ubudev/submit/heichips25-ethernet/src/heichips25_ethernet.sv:16.23-16.26"
          }
        },
        "ena": {
          "hide_name": 0,
          "bits": [ 18 ],
          "attributes": {
            "src": "/home/ubudev/submit/heichips25-ethernet/src/heichips25_ethernet.sv:15.23-15.26"
          }
        },
        "ethernet_dn": {
          "hide_name": 0,
          "bits": [ 22 ],
          "attributes": {
            "src": "/home/ubudev/submit/heichips25-ethernet/src/heichips25_ethernet.sv:19.23-19.34"
          }
        },
        "ethernet_dp": {
          "hide_name": 0,
          "bits": [ 21 ],
          "attributes": {
            "src": "/home/ubudev/submit/heichips25-ethernet/src/heichips25_ethernet.sv:18.23-18.34"
          }
        },
        "in_n": {
          "hide_name": 0,
          "bits": [ 23 ],
          "attributes": {
            "src": "/home/ubudev/submit/heichips25-ethernet/src/heichips25_ethernet.sv:32.10-32.14"
          }
        },
        "rst_n": {
          "hide_name": 0,
          "bits": [ 20 ],
          "attributes": {
            "src": "/home/ubudev/submit/heichips25-ethernet/src/heichips25_ethernet.sv:17.23-17.28"
          }
        },
        "ui_in": {
          "hide_name": 0,
          "bits": [ 2, 3, 4, 5, 6, 7, 8, 9 ],
          "attributes": {
            "src": "/home/ubudev/submit/heichips25-ethernet/src/heichips25_ethernet.sv:10.23-10.28"
          }
        },
        "uio_in": {
          "hide_name": 0,
          "bits": [ 10, 11, 12, 13, 14, 15, 16, 17 ],
          "attributes": {
            "src": "/home/ubudev/submit/heichips25-ethernet/src/heichips25_ethernet.sv:12.23-12.29"
          }
        },
        "uio_oe": {
          "hide_name": 0,
          "bits": [ "0", "0", "0", "0", "0", "0", "0", "0" ],
          "attributes": {
            "src": "/home/ubudev/submit/heichips25-ethernet/src/heichips25_ethernet.sv:14.23-14.29"
          }
        },
        "uio_out": {
          "hide_name": 0,
          "bits": [ "0", "0", "0", "0", "0", "0", "0", "0" ],
          "attributes": {
            "src": "/home/ubudev/submit/heichips25-ethernet/src/heichips25_ethernet.sv:13.23-13.30"
          }
        },
        "uo_out": {
          "hide_name": 0,
          "bits": [ "0", "0", "0", "0", "0", "0", "0", "0" ],
          "attributes": {
            "src": "/home/ubudev/submit/heichips25-ethernet/src/heichips25_ethernet.sv:11.23-11.29"
          }
        }
      }
    }
  }
}
